src/ascii_to_bin.vhd


library ieee;
use ieee.std_logic_1164.all;  
use ieee.numeric_std.all;


entity ascii_to_bin is
    port (
        a       : in  unsigned(5 downto 0);
        
        b       : out std_logic_vector(5 downto 0)
    );
end entity ascii_to_bin;


architecture behavioral of ascii_to_bin is 

begin

    b <= std_logic_vector(a);


end architecture behavioral;

test/tb/tb_ascii_to_bin.vhd
library ieee;
use ieee.std_logic_1164.all;
use ieee.numeric_std.all;

entity tb_ascii_to_bin is
end entity tb_ascii_to_bin;

architecture behavior of tb_ascii_to_bin is

    component ascii_to_bin is
        port (
            a : in  unsigned(5 downto 0);
            b : out std_logic_vector(5 downto 0)
        );
    end component;

    signal a : unsigned(5 downto 0) := (others => '0');
    signal b : std_logic_vector(5 downto 0);

begin

    uut: ascii_to_bin
        port map (
            a => a,
            b => b
        );

    stim_proc: process
    begin
        for i in 30 to 50 loop
            a <= to_unsigned(i, 6);
            wait for 10 ns;
        end loop;

        wait;
    end process;

end architecture behavior;

test/wave/tb_ascii_to_bin.vcd
$date
  Thu Sep 24 17:47:38 2026
$end
$version
  GHDL v0
$end
$timescale
  1 fs
$end
$scope module standard $end
$upscope $end
$scope module std_logic_1164 $end
$upscope $end
$scope module numeric_std $end
$upscope $end
$scope module tb_ascii_to_bin $end
$var reg 6 ! a[5:0] $end
$var reg 6 " b[5:0] $end
$scope module uut $end
$var reg 6 # a[5:0] $end
$var reg 6 $ b[5:0] $end
$upscope $end
$upscope $end
$enddefinitions $end
#0
b011110 !
b011110 "
b011110 #
b011110 $
#10000000
b011111 !
b011111 "
b011111 #
b011111 $
#20000000
b100000 !
b100000 "
b100000 #
b100000 $
#30000000
b100001 !
b100001 "
b100001 #
b100001 $
#40000000
b100010 !
b100010 "
b100010 #
b100010 $
#50000000
b100011 !
b100011 "
b100011 #
b100011 $
#60000000
b100100 !
b100100 "
b100100 #
b100100 $
#70000000
b100101 !
b100101 "
b100101 #
b100101 $
#80000000
b100110 !
b100110 "
b100110 #
b100110 $
#90000000
b100111 !
b100111 "
b100111 #
b100111 $
#100000000
b101000 !
b101000 "
b101000 #
b101000 $
#110000000
b101001 !
b101001 "
b101001 #
b101001 $
#120000000
b101010 !
b101010 "
b101010 #
b101010 $
#130000000
b101011 !
b101011 "
b101011 #
b101011 $
#140000000
b101100 !
b101100 "
b101100 #
b101100 $
#150000000
b101101 !
b101101 "
b101101 #
b101101 $
#160000000
b101110 !
b101110 "
b101110 #
b101110 $
#170000000
b101111 !
b101111 "
b101111 #
b101111 $
#180000000
b110000 !
b110000 "
b110000 #
b110000 $
#190000000
b110001 !
b110001 "
b110001 #
b110001 $
#200000000
b110010 !
b110010 "
b110010 #
b110010 $
